{
	"version": "v 0.0.38",
	"date": "2026-01-12 11:45:23 +0100",
	"commit_hash": "",
	"commit_message": "aggiornamento 2026 01 12 11:45 [v 0.0.38]",
	"changes": [
		{
			"file": "artefatti/artefatto-necromante.md",
			"display_name": "artefatto-necromante",
			"status": "Modified",
			"diff": "commit a4430862689e8a668d9c2f6319479e6fe7f685c1\nAuthor: RickyMandich <ricky.mandich@gmail.com>\nDate:   Mon Jan 12 11:45:23 2026 +0100\n\n    aggiornamento 2026 01 12 11:45 [v 0.0.38]\n\ndiff --git a/artefatti/artefatto-necromante.md b/artefatti/artefatto-necromante.md\nindex ccba933..ef5e74d 100644\n--- a/artefatti/artefatto-necromante.md\n+++ b/artefatti/artefatto-necromante.md\n@@ -1,3 +1,21 @@\n+SWARM PEST\n+*1rd-level, Necromancy*  \n+\n+- **Casting time:** 1 action\n+- **Range:** 9m\n+- **Components:** V, S\n+- **Duration:** Concentration, up to 1 minute\n+\n+A swarm of insects springs to life at your fingertips and flies to a creature within range. A creature that fails on a dexterity saving throw takes 1d6 poison damage, or half as much on a success.\n+\n+On subsequent turns, you can direct the swarm to attack another creature within range, or move back to you, as a bonus action. If the swarm ever leaves the range, the spell ends.\n+\n+**At Higher Levels.** When cast using a 2nd level Spell-slot, the damage increases by 1d6 for every level above 2nd.\n+\n+**Classes**: Wizard\n+\n+*Source: SRD / Basic Rules*\n+---\n # appunti da inserire\n SWARM PEST\n 1st-Level Necromancy\n"
		},
		{
			"file": "definizioni/template/incantesimi.md",
			"display_name": "Incantesimi",
			"status": "Added",
			"diff": "commit a4430862689e8a668d9c2f6319479e6fe7f685c1\nAuthor: RickyMandich <ricky.mandich@gmail.com>\nDate:   Mon Jan 12 11:45:23 2026 +0100\n\n    aggiornamento 2026 01 12 11:45 [v 0.0.38]\n\ndiff --git a/definizioni/template/incantesimi.md b/definizioni/template/incantesimi.md\nnew file mode 100644\nindex 0000000..646e594\n--- /dev/null\n+++ b/definizioni/template/incantesimi.md\n@@ -0,0 +1,13 @@\n+[nome incantesimo]\n+*[livello]° livello, [scuola dimagia]*\n+\n+- **Tempo di lancio:**\n+- **Gittata:**\n+- **Componenti:**\n+- **Durata:**\n+\n+[descrizione]\n+\n+**Ai livelli superiori:**\n+\n+**Classi**:\n\\ No newline at end of file\n"
		}
	]
}
